library/__init__.py
library/r53collector.py
scripts/__init__.py
scripts/r53collector.py
r53collector-1.2.28.dist-info/LICENSE
r53collector-1.2.28.dist-info/METADATA
r53collector-1.2.28.dist-info/WHEEL
r53collector-1.2.28.dist-info/entry_points.txt
r53collector-1.2.28.dist-info/top_level.txt
r53collector-1.2.28.dist-info/RECORD
